django_gdm-0.3.dist-info/DESCRIPTION.rst
django_gdm-0.3.dist-info/METADATA
django_gdm-0.3.dist-info/metadata.json
django_gdm-0.3.dist-info/RECORD
django_gdm-0.3.dist-info/top_level.txt
django_gdm-0.3.dist-info/WHEEL
gdm/__init__.py
gdm/admin.py
gdm/tests.py
gdm/views.py
gdm/models/.DS_Store
gdm/models/__init__.py
gdm/models/timeline.py
gdm/models/tree.py
